{"hu":[{"datetime":"202209190000","value":"80"},{"datetime":"202209190600","value":"65"},{"datetime":"202209191200","value":"75"},{"datetime":"202209191800","value":"85"},{"datetime":"202209200000","value":"80"},{"datetime":"202209200600","value":"70"},{"datetime":"202209201200","value":"85"},{"datetime":"202209201800","value":"95"},{"datetime":"202209210000","value":"95"},{"datetime":"202209210600","value":"75"},{"datetime":"202209211200","value":"85"},{"datetime":"202209211800","value":"95"}],"humax":[{"datetime":"202209191200","value":"90"},{"datetime":"202209201200","value":"90"},{"datetime":"202209211200","value":"95"}],"tmax":[{"datetime":"202209191200","value_c":"33","value_f":"91.4"},{"datetime":"202209201200","value_c":"32","value_f":"89.6"},{"datetime":"202209211200","value_c":"32","value_f":"89.6"}],"humin":[{"datetime":"202209191200","value":"65"},{"datetime":"202209201200","value":"70"},{"datetime":"202209211200","value":"75"}],"tmin":[{"datetime":"202209191200","value_c":"24","value_f":"75.2"},{"datetime":"202209201200","value_c":"23","value_f":"73.4"},{"datetime":"202209211200","value_c":"24","value_f":"75.2"}],"t":[{"datetime":"202209190000","value_c":"26","value_f":"78.8"},{"datetime":"202209190600","value_c":"33","value_f":"91.4"},{"datetime":"202209191200","value_c":"29","value_f":"84.2"},{"datetime":"202209191800","value_c":"23","value_f":"73.4"},{"datetime":"202209200000","value_c":"28","value_f":"82.4"},{"datetime":"202209200600","value_c":"32","value_f":"89.6"},{"datetime":"202209201200","value_c":"28","value_f":"82.4"},{"datetime":"202209201800","value_c":"24","value_f":"75.2"},{"datetime":"202209210000","value_c":"28","value_f":"82.4"},{"datetime":"202209210600","value_c":"32","value_f":"89.6"},{"datetime":"202209211200","value_c":"28","value_f":"82.4"},{"datetime":"202209211800","value_c":"24","value_f":"75.2"}],"weather":[{"datetime":"202209190000","value":"1"},{"datetime":"202209190600","value":"60"},{"datetime":"202209191200","value":"3"},{"datetime":"202209191800","value":"3"},{"datetime":"202209200000","value":"3"},{"datetime":"202209200600","value":"60"},{"datetime":"202209201200","value":"3"},{"datetime":"202209201800","value":"3"},{"datetime":"202209210000","value":"60"},{"datetime":"202209210600","value":"1"},{"datetime":"202209211200","value":"3"},{"datetime":"202209211800","value":"3"}],"wd":[{"datetime":"202209190000","value_deg":"112.5","value_CARD":"ESE","value_SEXA":"11230"},{"datetime":"202209190600","value_deg":"112.5","value_CARD":"ESE","value_SEXA":"11230"},{"datetime":"202209191200","value_deg":"112.5","value_CARD":"ESE","value_SEXA":"11230"},{"datetime":"202209191800","value_deg":"112.5","value_CARD":"ESE","value_SEXA":"11230"},{"datetime":"202209200000","value_deg":"112.5","value_CARD":"ESE","value_SEXA":"11230"},{"datetime":"202209200600","value_deg":"112.5","value_CARD":"ESE","value_SEXA":"11230"},{"datetime":"202209201200","value_deg":"112.5","value_CARD":"ESE","value_SEXA":"11230"},{"datetime":"202209201800","value_deg":"112.5","value_CARD":"ESE","value_SEXA":"11230"},{"datetime":"202209210000","value_deg":"112.5","value_CARD":"ESE","value_SEXA":"11230"},{"datetime":"202209210600","value_deg":"112.5","value_CARD":"ESE","value_SEXA":"11230"},{"datetime":"202209211200","value_deg":"112.5","value_CARD":"ESE","value_SEXA":"11230"},{"datetime":"202209211800","value_deg":"112.5","value_CARD":"ESE","value_SEXA":"11230"}],"ws":[{"datetime":"202209190000","value_Kt":"5","value_MPH":"5.75389725","value_KPH":"9.26","value_MS":"2.57222222"},{"datetime":"202209190600","value_Kt":"5","value_MPH":"5.75389725","value_KPH":"9.26","value_MS":"2.57222222"},{"datetime":"202209191200","value_Kt":"5","value_MPH":"5.75389725","value_KPH":"9.26","value_MS":"2.57222222"},{"datetime":"202209191800","value_Kt":"5","value_MPH":"5.75389725","value_KPH":"9.26","value_MS":"2.57222222"},{"datetime":"202209200000","value_Kt":"10","value_MPH":"11.5077945","value_KPH":"18.52","value_MS":"5.14444444"},{"datetime":"202209200600","value_Kt":"10","value_MPH":"11.5077945","value_KPH":"18.52","value_MS":"5.14444444"},{"datetime":"202209201200","value_Kt":"5","value_MPH":"5.75389725","value_KPH":"9.26","value_MS":"2.57222222"},{"datetime":"202209201800","value_Kt":"5","value_MPH":"5.75389725","value_KPH":"9.26","value_MS":"2.57222222"},{"datetime":"202209210000","value_Kt":"10","value_MPH":"11.5077945","value_KPH":"18.52","value_MS":"5.14444444"},{"datetime":"202209210600","value_Kt":"10","value_MPH":"11.5077945","value_KPH":"18.52","value_MS":"5.14444444"},{"datetime":"202209211200","value_Kt":"10","value_MPH":"11.5077945","value_KPH":"18.52","value_MS":"5.14444444"},{"datetime":"202209211800","value_Kt":"10","value_MPH":"11.5077945","value_KPH":"18.52","value_MS":"5.14444444"}]}