{"hu":[{"datetime":"202206120000","value":"80"},{"datetime":"202206120600","value":"70"},{"datetime":"202206121200","value":"85"},{"datetime":"202206121800","value":"95"},{"datetime":"202206130000","value":"80"},{"datetime":"202206130600","value":"70"},{"datetime":"202206131200","value":"85"},{"datetime":"202206131800","value":"95"},{"datetime":"202206140000","value":"85"},{"datetime":"202206140600","value":"80"},{"datetime":"202206141200","value":"85"},{"datetime":"202206141800","value":"95"}],"humax":[{"datetime":"202206121200","value":"90"},{"datetime":"202206131200","value":"95"},{"datetime":"202206141200","value":"95"}],"tmax":[{"datetime":"202206121200","value_c":"32","value_f":"89.6"},{"datetime":"202206131200","value_c":"32","value_f":"89.6"},{"datetime":"202206141200","value_c":"33","value_f":"91.4"}],"humin":[{"datetime":"202206121200","value":"70"},{"datetime":"202206131200","value":"70"},{"datetime":"202206141200","value":"80"}],"tmin":[{"datetime":"202206121200","value_c":"25","value_f":"77"},{"datetime":"202206131200","value_c":"25","value_f":"77"},{"datetime":"202206141200","value_c":"25","value_f":"77"}],"t":[{"datetime":"202206120000","value_c":"27","value_f":"80.6"},{"datetime":"202206120600","value_c":"32","value_f":"89.6"},{"datetime":"202206121200","value_c":"27","value_f":"80.6"},{"datetime":"202206121800","value_c":"25","value_f":"77"},{"datetime":"202206130000","value_c":"27","value_f":"80.6"},{"datetime":"202206130600","value_c":"32","value_f":"89.6"},{"datetime":"202206131200","value_c":"28","value_f":"82.4"},{"datetime":"202206131800","value_c":"25","value_f":"77"},{"datetime":"202206140000","value_c":"25","value_f":"77"},{"datetime":"202206140600","value_c":"33","value_f":"91.4"},{"datetime":"202206141200","value_c":"29","value_f":"84.2"},{"datetime":"202206141800","value_c":"27","value_f":"80.6"}],"weather":[{"datetime":"202206120000","value":"60"},{"datetime":"202206120600","value":"60"},{"datetime":"202206121200","value":"60"},{"datetime":"202206121800","value":"60"},{"datetime":"202206130000","value":"61"},{"datetime":"202206130600","value":"60"},{"datetime":"202206131200","value":"60"},{"datetime":"202206131800","value":"60"},{"datetime":"202206140000","value":"1"},{"datetime":"202206140600","value":"60"},{"datetime":"202206141200","value":"60"},{"datetime":"202206141800","value":"3"}],"wd":[{"datetime":"202206120000","value_deg":"90","value_CARD":"E","value_SEXA":"9000"},{"datetime":"202206120600","value_deg":"90","value_CARD":"E","value_SEXA":"9000"},{"datetime":"202206121200","value_deg":"90","value_CARD":"E","value_SEXA":"9000"},{"datetime":"202206121800","value_deg":"90","value_CARD":"E","value_SEXA":"9000"},{"datetime":"202206130000","value_deg":"90","value_CARD":"E","value_SEXA":"9000"},{"datetime":"202206130600","value_deg":"90","value_CARD":"E","value_SEXA":"9000"},{"datetime":"202206131200","value_deg":"90","value_CARD":"E","value_SEXA":"9000"},{"datetime":"202206131800","value_deg":"90","value_CARD":"E","value_SEXA":"9000"},{"datetime":"202206140000","value_deg":"90","value_CARD":"E","value_SEXA":"9000"},{"datetime":"202206140600","value_deg":"90","value_CARD":"E","value_SEXA":"9000"},{"datetime":"202206141200","value_deg":"90","value_CARD":"E","value_SEXA":"9000"},{"datetime":"202206141800","value_deg":"90","value_CARD":"E","value_SEXA":"9000"}],"ws":[{"datetime":"202206120000","value_Kt":"5","value_MPH":"5.75389725","value_KPH":"9.26","value_MS":"2.57222222"},{"datetime":"202206120600","value_Kt":"10","value_MPH":"11.5077945","value_KPH":"18.52","value_MS":"5.14444444"},{"datetime":"202206121200","value_Kt":"10","value_MPH":"11.5077945","value_KPH":"18.52","value_MS":"5.14444444"},{"datetime":"202206121800","value_Kt":"5","value_MPH":"5.75389725","value_KPH":"9.26","value_MS":"2.57222222"},{"datetime":"202206130000","value_Kt":"5","value_MPH":"5.75389725","value_KPH":"9.26","value_MS":"2.57222222"},{"datetime":"202206130600","value_Kt":"10","value_MPH":"11.5077945","value_KPH":"18.52","value_MS":"5.14444444"},{"datetime":"202206131200","value_Kt":"10","value_MPH":"11.5077945","value_KPH":"18.52","value_MS":"5.14444444"},{"datetime":"202206131800","value_Kt":"5","value_MPH":"5.75389725","value_KPH":"9.26","value_MS":"2.57222222"},{"datetime":"202206140000","value_Kt":"10","value_MPH":"11.5077945","value_KPH":"18.52","value_MS":"5.14444444"},{"datetime":"202206140600","value_Kt":"10","value_MPH":"11.5077945","value_KPH":"18.52","value_MS":"5.14444444"},{"datetime":"202206141200","value_Kt":"10","value_MPH":"11.5077945","value_KPH":"18.52","value_MS":"5.14444444"},{"datetime":"202206141800","value_Kt":"10","value_MPH":"11.5077945","value_KPH":"18.52","value_MS":"5.14444444"}]}